<mvc:View controllerName="com.knpl.pragati.OrganizationSetup.controller.Role" class="sapUiSizeCompact" xmlns:mvc="sap.ui.core.mvc" displayBlock="true" xmlns="sap.m"
xmlns:l="sap.ui.layout">
<Page
		title="{i18n>detailPageTitle}"
		showNavButton="true"
		navButtonPress=".onNavBack">
	<l:VerticalLayout class="sapUiContentPadding" width="100%">
		<Label text="Role" labelFor="role" design="Bold" />
		<Input id="role" required="true" value="{data>Role}"/>

        <Label text="Description" labelFor="description" design="Bold" />
		<Input id="description" required="true" value="{data>Description}"/>

		

        <Button text="Update"
						press="update"
						ariaDescribedBy="defaultButtonDescription genericButtonDescription">
					
				</Button>
               
                
                 
	</l:VerticalLayout>
    </Page>
</mvc:View>
